{"name":"build-javascript","namedChunkGroups":{"polyfill":{"name":"polyfill","assets":[{"name":"webpack-runtime-a55b0e9b110feb5e71f9.js","size":4518},{"name":"polyfill-033f8cc93700f716eb7a.js","size":85011}],"filteredAssets":0,"assetsSize":89529,"filteredAuxiliaryAssets":2,"auxiliaryAssetsSize":228711},"app":{"name":"app","assets":[{"name":"webpack-runtime-a55b0e9b110feb5e71f9.js","size":4518},{"name":"framework-46fb7fe4c27fe536267a.js","size":140719},{"name":"app-52a1b391f582177d72e4.js","size":143517}],"filteredAssets":0,"assetsSize":288754,"filteredAuxiliaryAssets":3,"auxiliaryAssetsSize":887404},"component---src-pages-404-js":{"name":"component---src-pages-404-js","assets":[{"name":"component---src-pages-404-js-57cd9a90b4cd71e484b3.js","size":782}],"filteredAssets":0,"assetsSize":782,"filteredAuxiliaryAssets":1,"auxiliaryAssetsSize":1760},"component---src-pages-about-js":{"name":"component---src-pages-about-js","assets":[{"name":"styles.0974a3a0f61b3e17b2a5.css","size":2105},{"name":"component---src-pages-about-js-ade032e673f8ff1acff0.js","size":279}],"filteredAssets":0,"assetsSize":2384,"filteredAuxiliaryAssets":1,"auxiliaryAssetsSize":382},"component---src-pages-goodbye-js":{"name":"component---src-pages-goodbye-js","assets":[{"name":"styles.0974a3a0f61b3e17b2a5.css","size":2105},{"name":"component---src-pages-goodbye-js-23526f2571a584a3f35a.js","size":877}],"filteredAssets":0,"assetsSize":2982,"filteredAuxiliaryAssets":3,"auxiliaryAssetsSize":550654},"component---src-pages-index-js":{"name":"component---src-pages-index-js","assets":[{"name":"styles.0974a3a0f61b3e17b2a5.css","size":2105},{"name":"2e6bde05-dfd1e87db622261e94b9.js","size":694},{"name":"2cca2479-3485bd0a98182c00e275.js","size":1193},{"name":"component---src-pages-index-js-92c6daee1f95dbe4a6e7.js","size":7591}],"filteredAssets":0,"assetsSize":11583,"filteredAuxiliaryAssets":5,"auxiliaryAssetsSize":1829932}},"assetsByChunkName":{"polyfill":["webpack-runtime-a55b0e9b110feb5e71f9.js","polyfill-033f8cc93700f716eb7a.js"],"app":["webpack-runtime-a55b0e9b110feb5e71f9.js","framework-46fb7fe4c27fe536267a.js","app-52a1b391f582177d72e4.js"],"component---src-pages-404-js":["component---src-pages-404-js-57cd9a90b4cd71e484b3.js"],"component---src-pages-about-js":["styles.0974a3a0f61b3e17b2a5.css","component---src-pages-about-js-ade032e673f8ff1acff0.js"],"component---src-pages-goodbye-js":["styles.0974a3a0f61b3e17b2a5.css","component---src-pages-goodbye-js-23526f2571a584a3f35a.js"],"component---src-pages-index-js":["styles.0974a3a0f61b3e17b2a5.css","2e6bde05-dfd1e87db622261e94b9.js","2cca2479-3485bd0a98182c00e275.js","component---src-pages-index-js-92c6daee1f95dbe4a6e7.js"]},"childAssetsByChunkName":{}}